[INFO] Scanning for projects...
[INFO] 
[INFO] ---------------< cs.msu.edu:csci-468-spring2024-private >---------------
[INFO] Building csci-468-spring2024-private 1.0-SNAPSHOT
[INFO]   from pom.xml
[INFO] --------------------------------[ jar ]---------------------------------
[INFO] 
[INFO] --- resources:3.3.1:resources (default-resources) @ csci-468-spring2024-private ---
[WARNING] Using platform encoding (UTF-8 actually) to copy filtered resources, i.e. build is platform dependent!
[INFO] Copying 5 resources from src/main/resources to target/classes
[INFO] 
[INFO] --- compiler:3.1:compile (default-compile) @ csci-468-spring2024-private ---
[INFO] Changes detected - recompiling the module!
[WARNING] File encoding has not been set, using platform encoding UTF-8, i.e. build is platform dependent!
[INFO] Compiling 47 source files to /Users/carson/Projects/msu/csci-468-spring2024/grading/scripts/repos/cooper_senior/target/classes
[WARNING] /Users/carson/Projects/msu/csci-468-spring2024/grading/scripts/repos/cooper_senior/src/main/java/edu/montana/csci/csci468/bytecode/MethodGenerator.java: /Users/carson/Projects/msu/csci-468-spring2024/grading/scripts/repos/cooper_senior/src/main/java/edu/montana/csci/csci468/bytecode/MethodGenerator.java uses or overrides a deprecated API.
[WARNING] /Users/carson/Projects/msu/csci-468-spring2024/grading/scripts/repos/cooper_senior/src/main/java/edu/montana/csci/csci468/bytecode/MethodGenerator.java: Recompile with -Xlint:deprecation for details.
[WARNING] /Users/carson/Projects/msu/csci-468-spring2024/grading/scripts/repos/cooper_senior/src/main/java/edu/montana/csci/csci468/parser/CatscriptType.java: Some input files use unchecked or unsafe operations.
[WARNING] /Users/carson/Projects/msu/csci-468-spring2024/grading/scripts/repos/cooper_senior/src/main/java/edu/montana/csci/csci468/parser/CatscriptType.java: Recompile with -Xlint:unchecked for details.
[INFO] 
[INFO] --- resources:3.3.1:testResources (default-testResources) @ csci-468-spring2024-private ---
[WARNING] Using platform encoding (UTF-8 actually) to copy filtered resources, i.e. build is platform dependent!
[INFO] skip non existing resourceDirectory /Users/carson/Projects/msu/csci-468-spring2024/grading/scripts/repos/cooper_senior/src/test/resources
[INFO] 
[INFO] --- compiler:3.1:testCompile (default-testCompile) @ csci-468-spring2024-private ---
[INFO] Nothing to compile - all classes are up to date
[INFO] 
[INFO] --- surefire:2.22.1:test (default-test) @ csci-468-spring2024-private ---
[INFO] 
[INFO] -------------------------------------------------------
[INFO]  T E S T S
[INFO] -------------------------------------------------------
[INFO] Running edu.montana.csci.csci468.bytecode.CatscriptStatementExecutionTest
functionDefStatement
IdentifierExpression
IE int
IdentifierExpression
IE int
funcCallEx
IdentifierExpression
IE int
funcCallEx
local
IdentifierExpression
IE int
IdentifierExpression
IE int
 JVM Bytecode ===================================

// class version 49.0 (49)
// access flags 0x1
public class edu/montana/csci/csci466/bytecode/CatScriptProgram2 extends edu/montana/csci/csci468/parser/statements/CatScriptProgram {


  // access flags 0x1
  public <init>()V
    ALOAD 0
    INVOKESPECIAL edu/montana/csci/csci468/parser/statements/CatScriptProgram.<init> ()V
    RETURN
    MAXSTACK = 1
    MAXLOCALS = 1

  // access flags 0x1
  public execute()V
    NEW java/util/ArrayList
    DUP
    INVOKESPECIAL java/util/ArrayList.<init> ()V
    DUP
    LDC 1
    INVOKESTATIC java/lang/Integer.valueOf (I)Ljava/lang/Integer;
    INVOKEVIRTUAL java/util/ArrayList.add (Ljava/lang/Object;)Z
    POP
    DUP
    LDC 2
    INVOKESTATIC java/lang/Integer.valueOf (I)Ljava/lang/Integer;
    INVOKEVIRTUAL java/util/ArrayList.add (Ljava/lang/Object;)Z
    POP
    DUP
    LDC 3
    INVOKESTATIC java/lang/Integer.valueOf (I)Ljava/lang/Integer;
    INVOKEVIRTUAL java/util/ArrayList.add (Ljava/lang/Object;)Z
    POP
    INVOKEINTERFACE java/util/List.iterator ()Ljava/util/Iterator; (itf)
    ASTORE 1
   L0
   FRAME FULL [edu/montana/csci/csci466/bytecode/CatScriptProgram2 java/util/Iterator] []
    ALOAD 1
    INVOKEINTERFACE java/util/Iterator.hasNext ()Z (itf)
    IFEQ L1
    ALOAD 1
    INVOKEINTERFACE java/util/Iterator.next ()Ljava/lang/Object; (itf)
    CHECKCAST java/lang/Integer
    ASTORE 2
    ALOAD 2
    INVOKEVIRTUAL java/lang/Integer.intValue ()I
    ISTORE 2
    ILOAD 2
    ISTORE 3
    ALOAD 0
    ILOAD 3
    INVOKESTATIC java/lang/Integer.valueOf (I)Ljava/lang/Integer;
    INVOKEVIRTUAL edu/montana/csci/csci466/bytecode/CatScriptProgram2.print (Ljava/lang/Object;)V
    GOTO L0
   L1
   FRAME FULL [edu/montana/csci/csci466/bytecode/CatScriptProgram2 java/util/Iterator] []
    RETURN
    MAXSTACK = 3
    MAXLOCALS = 4
}


 ================================================
global
IdentifierExpression
 JVM Bytecode ===================================

// class version 49.0 (49)
// access flags 0x1
public class edu/montana/csci/csci466/bytecode/CatScriptProgram3 extends edu/montana/csci/csci468/parser/statements/CatScriptProgram {


  // access flags 0x2
  private I x

  // access flags 0x1
  public <init>()V
    ALOAD 0
    INVOKESPECIAL edu/montana/csci/csci468/parser/statements/CatScriptProgram.<init> ()V
    RETURN
    MAXSTACK = 1
    MAXLOCALS = 1

  // access flags 0x1
  public execute()V
    ALOAD 0
    LDC 1
    PUTFIELD edu/montana/csci/csci466/bytecode/CatScriptProgram3.x : I
    ALOAD 0
    ALOAD 0
    GETFIELD edu/montana/csci/csci466/bytecode/CatScriptProgram3.x : I
    INVOKESTATIC java/lang/Integer.valueOf (I)Ljava/lang/Integer;
    INVOKEVIRTUAL edu/montana/csci/csci466/bytecode/CatScriptProgram3.print (Ljava/lang/Object;)V
    RETURN
    MAXSTACK = 2
    MAXLOCALS = 1
}


 ================================================
global
global
IdentifierExpression
IdentifierExpression
 JVM Bytecode ===================================

// class version 49.0 (49)
// access flags 0x1
public class edu/montana/csci/csci466/bytecode/CatScriptProgram4 extends edu/montana/csci/csci468/parser/statements/CatScriptProgram {


  // access flags 0x2
  private I x

  // access flags 0x2
  private I y

  // access flags 0x1
  public <init>()V
    ALOAD 0
    INVOKESPECIAL edu/montana/csci/csci468/parser/statements/CatScriptProgram.<init> ()V
    RETURN
    MAXSTACK = 1
    MAXLOCALS = 1

  // access flags 0x1
  public execute()V
    ALOAD 0
    LDC 1
    PUTFIELD edu/montana/csci/csci466/bytecode/CatScriptProgram4.x : I
    ALOAD 0
    ALOAD 0
    GETFIELD edu/montana/csci/csci466/bytecode/CatScriptProgram4.x : I
    PUTFIELD edu/montana/csci/csci466/bytecode/CatScriptProgram4.y : I
    ALOAD 0
    ALOAD 0
    GETFIELD edu/montana/csci/csci466/bytecode/CatScriptProgram4.y : I
    INVOKESTATIC java/lang/Integer.valueOf (I)Ljava/lang/Integer;
    INVOKEVIRTUAL edu/montana/csci/csci466/bytecode/CatScriptProgram4.print (Ljava/lang/Object;)V
    RETURN
    MAXSTACK = 2
    MAXLOCALS = 1
}


 ================================================
global
edu/montana/csci/csci468/parser/CatscriptType
IdentifierExpression
 JVM Bytecode ===================================

// class version 49.0 (49)
// access flags 0x1
public class edu/montana/csci/csci466/bytecode/CatScriptProgram5 extends edu/montana/csci/csci468/parser/statements/CatScriptProgram {


  // access flags 0x2
  private Ljava/lang/Object; x

  // access flags 0x1
  public <init>()V
    ALOAD 0
    INVOKESPECIAL edu/montana/csci/csci468/parser/statements/CatScriptProgram.<init> ()V
    RETURN
    MAXSTACK = 1
    MAXLOCALS = 1

  // access flags 0x1
  public execute()V
    ALOAD 0
    ACONST_NULL
    PUTFIELD edu/montana/csci/csci466/bytecode/CatScriptProgram5.x : Ljava/lang/Object;
    ALOAD 0
    ALOAD 0
    ACONST_NULL
    INVOKEVIRTUAL edu/montana/csci/csci466/bytecode/CatScriptProgram5.print (Ljava/lang/Object;)V
    RETURN
    MAXSTACK = 3
    MAXLOCALS = 1
}


 ================================================
functionDefStatement
IdentifierExpression
IE object
funcCallEx
funcCallEx
funcCallEx
 JVM Bytecode ===================================

// class version 49.0 (49)
// access flags 0x1
public class edu/montana/csci/csci466/bytecode/CatScriptProgram6 extends edu/montana/csci/csci468/parser/statements/CatScriptProgram {


  // access flags 0x1
  public <init>()V
    ALOAD 0
    INVOKESPECIAL edu/montana/csci/csci468/parser/statements/CatScriptProgram.<init> ()V
    RETURN
    MAXSTACK = 1
    MAXLOCALS = 1

  // access flags 0x1
  public execute()V
    ALOAD 0
    LDC 1
    INVOKESTATIC java/lang/Integer.valueOf (I)Ljava/lang/Integer;
    INVOKEVIRTUAL edu/montana/csci/csci466/bytecode/CatScriptProgram6.foo (Ljava/lang/Object;)V
    ALOAD 0
    LDC 2
    INVOKESTATIC java/lang/Integer.valueOf (I)Ljava/lang/Integer;
    INVOKEVIRTUAL edu/montana/csci/csci466/bytecode/CatScriptProgram6.foo (Ljava/lang/Object;)V
    ALOAD 0
    LDC 3
    INVOKESTATIC java/lang/Integer.valueOf (I)Ljava/lang/Integer;
    INVOKEVIRTUAL edu/montana/csci/csci466/bytecode/CatScriptProgram6.foo (Ljava/lang/Object;)V
    RETURN
    MAXSTACK = 2
    MAXLOCALS = 1

  // access flags 0x1
  public foo(Ljava/lang/Object;)V
    ALOAD 0
    ALOAD 1
    INVOKEVIRTUAL edu/montana/csci/csci466/bytecode/CatScriptProgram6.print (Ljava/lang/Object;)V
    RETURN
    MAXSTACK = 2
    MAXLOCALS = 2
}


 ================================================
functionDefStatement
returnStatement
IdentifierExpression
IE int
funcCallEx
functionDefStatement
local
returnStatement
IdentifierExpression
IE int
funcCallEx
 JVM Bytecode ===================================

// class version 49.0 (49)
// access flags 0x1
public class edu/montana/csci/csci466/bytecode/CatScriptProgram9 extends edu/montana/csci/csci468/parser/statements/CatScriptProgram {


  // access flags 0x1
  public <init>()V
    ALOAD 0
    INVOKESPECIAL edu/montana/csci/csci468/parser/statements/CatScriptProgram.<init> ()V
    RETURN
    MAXSTACK = 1
    MAXLOCALS = 1

  // access flags 0x1
  public execute()V
    LDC 1
    IFEQ L0
    ALOAD 0
    LDC 1
    INVOKESTATIC java/lang/Integer.valueOf (I)Ljava/lang/Integer;
    INVOKEVIRTUAL edu/montana/csci/csci466/bytecode/CatScriptProgram9.print (Ljava/lang/Object;)V
    GOTO L0
   L0
   FRAME FULL [edu/montana/csci/csci466/bytecode/CatScriptProgram9] []
    RETURN
    MAXSTACK = 2
    MAXLOCALS = 1
}


 ================================================
 JVM Bytecode ===================================

// class version 49.0 (49)
// access flags 0x1
public class edu/montana/csci/csci466/bytecode/CatScriptProgram10 extends edu/montana/csci/csci468/parser/statements/CatScriptProgram {


  // access flags 0x1
  public <init>()V
    ALOAD 0
    INVOKESPECIAL edu/montana/csci/csci468/parser/statements/CatScriptProgram.<init> ()V
    RETURN
    MAXSTACK = 1
    MAXLOCALS = 1

  // access flags 0x1
  public execute()V
    LDC 0
    IFEQ L0
    ALOAD 0
    LDC 1
    INVOKESTATIC java/lang/Integer.valueOf (I)Ljava/lang/Integer;
    INVOKEVIRTUAL edu/montana/csci/csci466/bytecode/CatScriptProgram10.print (Ljava/lang/Object;)V
    GOTO L0
   L0
   FRAME FULL [edu/montana/csci/csci466/bytecode/CatScriptProgram10] []
    RETURN
    MAXSTACK = 2
    MAXLOCALS = 1
}


 ================================================
 JVM Bytecode ===================================

// class version 49.0 (49)
// access flags 0x1
public class edu/montana/csci/csci466/bytecode/CatScriptProgram11 extends edu/montana/csci/csci468/parser/statements/CatScriptProgram {


  // access flags 0x1
  public <init>()V
    ALOAD 0
    INVOKESPECIAL edu/montana/csci/csci468/parser/statements/CatScriptProgram.<init> ()V
    RETURN
    MAXSTACK = 1
    MAXLOCALS = 1

  // access flags 0x1
  public execute()V
    LDC 1
    IFEQ L0
    ALOAD 0
    LDC 1
    INVOKESTATIC java/lang/Integer.valueOf (I)Ljava/lang/Integer;
    INVOKEVIRTUAL edu/montana/csci/csci466/bytecode/CatScriptProgram11.print (Ljava/lang/Object;)V
    GOTO L1
   L0
   FRAME FULL [edu/montana/csci/csci466/bytecode/CatScriptProgram11] []
    ALOAD 0
    LDC 2
    INVOKESTATIC java/lang/Integer.valueOf (I)Ljava/lang/Integer;
    INVOKEVIRTUAL edu/montana/csci/csci466/bytecode/CatScriptProgram11.print (Ljava/lang/Object;)V
   L1
   FRAME FULL [edu/montana/csci/csci466/bytecode/CatScriptProgram11] []
    RETURN
    MAXSTACK = 2
    MAXLOCALS = 1
}


 ================================================
 JVM Bytecode ===================================

// class version 49.0 (49)
// access flags 0x1
public class edu/montana/csci/csci466/bytecode/CatScriptProgram12 extends edu/montana/csci/csci468/parser/statements/CatScriptProgram {


  // access flags 0x1
  public <init>()V
    ALOAD 0
    INVOKESPECIAL edu/montana/csci/csci468/parser/statements/CatScriptProgram.<init> ()V
    RETURN
    MAXSTACK = 1
    MAXLOCALS = 1

  // access flags 0x1
  public execute()V
    LDC 0
    IFEQ L0
    ALOAD 0
    LDC 1
    INVOKESTATIC java/lang/Integer.valueOf (I)Ljava/lang/Integer;
    INVOKEVIRTUAL edu/montana/csci/csci466/bytecode/CatScriptProgram12.print (Ljava/lang/Object;)V
    GOTO L1
   L0
   FRAME FULL [edu/montana/csci/csci466/bytecode/CatScriptProgram12] []
    ALOAD 0
    LDC 2
    INVOKESTATIC java/lang/Integer.valueOf (I)Ljava/lang/Integer;
    INVOKEVIRTUAL edu/montana/csci/csci466/bytecode/CatScriptProgram12.print (Ljava/lang/Object;)V
   L1
   FRAME FULL [edu/montana/csci/csci466/bytecode/CatScriptProgram12] []
    RETURN
    MAXSTACK = 2
    MAXLOCALS = 1
}


 ================================================
IdentifierExpression
IE int
 JVM Bytecode ===================================

// class version 49.0 (49)
// access flags 0x1
public class edu/montana/csci/csci466/bytecode/CatScriptProgram13 extends edu/montana/csci/csci468/parser/statements/CatScriptProgram {


  // access flags 0x1
  public <init>()V
    ALOAD 0
    INVOKESPECIAL edu/montana/csci/csci468/parser/statements/CatScriptProgram.<init> ()V
    RETURN
    MAXSTACK = 1
    MAXLOCALS = 1

  // access flags 0x1
  public execute()V
    NEW java/util/ArrayList
    DUP
    INVOKESPECIAL java/util/ArrayList.<init> ()V
    DUP
    LDC 1
    INVOKESTATIC java/lang/Integer.valueOf (I)Ljava/lang/Integer;
    INVOKEVIRTUAL java/util/ArrayList.add (Ljava/lang/Object;)Z
    POP
    DUP
    LDC 2
    INVOKESTATIC java/lang/Integer.valueOf (I)Ljava/lang/Integer;
    INVOKEVIRTUAL java/util/ArrayList.add (Ljava/lang/Object;)Z
    POP
    DUP
    LDC 3
    INVOKESTATIC java/lang/Integer.valueOf (I)Ljava/lang/Integer;
    INVOKEVIRTUAL java/util/ArrayList.add (Ljava/lang/Object;)Z
    POP
    INVOKEINTERFACE java/util/List.iterator ()Ljava/util/Iterator; (itf)
    ASTORE 1
   L0
   FRAME FULL [edu/montana/csci/csci466/bytecode/CatScriptProgram13 java/util/Iterator] []
    ALOAD 1
    INVOKEINTERFACE java/util/Iterator.hasNext ()Z (itf)
    IFEQ L1
    ALOAD 1
    INVOKEINTERFACE java/util/Iterator.next ()Ljava/lang/Object; (itf)
    CHECKCAST java/lang/Integer
    ASTORE 2
    ALOAD 2
    INVOKEVIRTUAL java/lang/Integer.intValue ()I
    ISTORE 2
    ALOAD 0
    ILOAD 2
    INVOKESTATIC java/lang/Integer.valueOf (I)Ljava/lang/Integer;
    INVOKEVIRTUAL edu/montana/csci/csci466/bytecode/CatScriptProgram13.print (Ljava/lang/Object;)V
    GOTO L0
   L1
   FRAME FULL [edu/montana/csci/csci466/bytecode/CatScriptProgram13 java/util/Iterator] []
    RETURN
    MAXSTACK = 3
    MAXLOCALS = 3
}


 ================================================
 JVM Bytecode ===================================

// class version 49.0 (49)
// access flags 0x1
public class edu/montana/csci/csci466/bytecode/CatScriptProgram14 extends edu/montana/csci/csci468/parser/statements/CatScriptProgram {


  // access flags 0x1
  public <init>()V
    ALOAD 0
    INVOKESPECIAL edu/montana/csci/csci468/parser/statements/CatScriptProgram.<init> ()V
    RETURN
    MAXSTACK = 1
    MAXLOCALS = 1

  // access flags 0x1
  public execute()V
    ALOAD 0
    LDC 1
    INVOKESTATIC java/lang/Integer.valueOf (I)Ljava/lang/Integer;
    INVOKEVIRTUAL edu/montana/csci/csci466/bytecode/CatScriptProgram14.print (Ljava/lang/Object;)V
    RETURN
    MAXSTACK = 2
    MAXLOCALS = 1
}


 ================================================
 JVM Bytecode ===================================

// class version 49.0 (49)
// access flags 0x1
public class edu/montana/csci/csci466/bytecode/CatScriptProgram15 extends edu/montana/csci/csci468/parser/statements/CatScriptProgram {


  // access flags 0x1
  public <init>()V
    ALOAD 0
    INVOKESPECIAL edu/montana/csci/csci468/parser/statements/CatScriptProgram.<init> ()V
    RETURN
    MAXSTACK = 1
    MAXLOCALS = 1

  // access flags 0x1
  public execute()V
    ALOAD 0
    LDC 1
    INVOKESTATIC java/lang/Integer.valueOf (I)Ljava/lang/Integer;
    INVOKEVIRTUAL edu/montana/csci/csci466/bytecode/CatScriptProgram15.print (Ljava/lang/Object;)V
    ALOAD 0
    LDC 2
    INVOKESTATIC java/lang/Integer.valueOf (I)Ljava/lang/Integer;
    INVOKEVIRTUAL edu/montana/csci/csci466/bytecode/CatScriptProgram15.print (Ljava/lang/Object;)V
    RETURN
    MAXSTACK = 2
    MAXLOCALS = 1
}


 ================================================
 JVM Bytecode ===================================

// class version 49.0 (49)
// access flags 0x1
public class edu/montana/csci/csci466/bytecode/CatScriptProgram16 extends edu/montana/csci/csci468/parser/statements/CatScriptProgram {


  // access flags 0x1
  public <init>()V
    ALOAD 0
    INVOKESPECIAL edu/montana/csci/csci468/parser/statements/CatScriptProgram.<init> ()V
    RETURN
    MAXSTACK = 1
    MAXLOCALS = 1

  // access flags 0x1
  public execute()V
    ALOAD 0
    LDC 1
    INVOKESTATIC java/lang/Boolean.valueOf (Z)Ljava/lang/Boolean;
    INVOKEVIRTUAL edu/montana/csci/csci466/bytecode/CatScriptProgram16.print (Ljava/lang/Object;)V
    RETURN
    MAXSTACK = 2
    MAXLOCALS = 1
}


 ================================================
 JVM Bytecode ===================================

// class version 49.0 (49)
// access flags 0x1
public class edu/montana/csci/csci466/bytecode/CatScriptProgram17 extends edu/montana/csci/csci468/parser/statements/CatScriptProgram {


  // access flags 0x1
  public <init>()V
    ALOAD 0
    INVOKESPECIAL edu/montana/csci/csci468/parser/statements/CatScriptProgram.<init> ()V
    RETURN
    MAXSTACK = 1
    MAXLOCALS = 1

  // access flags 0x1
  public execute()V
    ALOAD 0
    NEW java/util/ArrayList
    DUP
    INVOKESPECIAL java/util/ArrayList.<init> ()V
    DUP
    LDC 1
    INVOKESTATIC java/lang/Integer.valueOf (I)Ljava/lang/Integer;
    INVOKEVIRTUAL java/util/ArrayList.add (Ljava/lang/Object;)Z
    POP
    DUP
    LDC 2
    INVOKESTATIC java/lang/Integer.valueOf (I)Ljava/lang/Integer;
    INVOKEVIRTUAL java/util/ArrayList.add (Ljava/lang/Object;)Z
    POP
    DUP
    LDC 3
    INVOKESTATIC java/lang/Integer.valueOf (I)Ljava/lang/Integer;
    INVOKEVIRTUAL java/util/ArrayList.add (Ljava/lang/Object;)Z
    POP
    INVOKEVIRTUAL edu/montana/csci/csci466/bytecode/CatScriptProgram17.print (Ljava/lang/Object;)V
    RETURN
    MAXSTACK = 4
    MAXLOCALS = 1
}


 ================================================
[ERROR] Tests run: 9, Failures: 0, Errors: 3, Skipped: 0, Time elapsed: 0.067 s <<< FAILURE! - in edu.montana.csci.csci468.bytecode.CatscriptStatementExecutionTest
[ERROR] recursiveFunctionWorksProperly  Time elapsed: 0.04 s  <<< ERROR!
java.lang.IllegalArgumentException: 
Error at instruction 3: Argument 1: expected I, but found R execute()V
00000 R  :  :     ALOAD 0
00001 R  : R  :     LDC 9
00002 R  : R I  :     INVOKESTATIC java/lang/Integer.valueOf (I)Ljava/lang/Integer;
00003 R  : R R  :     INVOKEVIRTUAL edu/montana/csci/csci466/bytecode/CatScriptProgram1.foo (I)V
00004 ?    :     RETURN


	at edu.montana.csci.csci468.bytecode.CatscriptStatementExecutionTest.recursiveFunctionWorksProperly(CatscriptStatementExecutionTest.java:72)
Caused by: org.objectweb.asm.tree.analysis.AnalyzerException: Error at instruction 3: Argument 1: expected I, but found R
	at edu.montana.csci.csci468.bytecode.CatscriptStatementExecutionTest.recursiveFunctionWorksProperly(CatscriptStatementExecutionTest.java:72)
Caused by: org.objectweb.asm.tree.analysis.AnalyzerException: Argument 1: expected I, but found R
	at edu.montana.csci.csci468.bytecode.CatscriptStatementExecutionTest.recursiveFunctionWorksProperly(CatscriptStatementExecutionTest.java:72)

[ERROR] returnStatementWorks  Time elapsed: 0.002 s  <<< ERROR!
java.lang.IllegalArgumentException: 
Error at instruction 4: Argument 1: expected I, but found R execute()V
00000 R  :  :     ALOAD 0
00001 R  : R  :     ALOAD 0
00002 R  : R R  :     LDC 9
00003 R  : R R I  :     INVOKESTATIC java/lang/Integer.valueOf (I)Ljava/lang/Integer;
00004 R  : R R R  :     INVOKEVIRTUAL edu/montana/csci/csci466/bytecode/CatScriptProgram7.foo (I)I
00005 ?     :     INVOKESTATIC java/lang/Integer.valueOf (I)Ljava/lang/Integer;
00006 ?     :     INVOKEVIRTUAL edu/montana/csci/csci466/bytecode/CatScriptProgram7.print (Ljava/lang/Object;)V
00007 ?     :     RETURN


	at edu.montana.csci.csci468.bytecode.CatscriptStatementExecutionTest.returnStatementWorks(CatscriptStatementExecutionTest.java:85)
Caused by: org.objectweb.asm.tree.analysis.AnalyzerException: Error at instruction 4: Argument 1: expected I, but found R
	at edu.montana.csci.csci468.bytecode.CatscriptStatementExecutionTest.returnStatementWorks(CatscriptStatementExecutionTest.java:85)
Caused by: org.objectweb.asm.tree.analysis.AnalyzerException: Argument 1: expected I, but found R
	at edu.montana.csci.csci468.bytecode.CatscriptStatementExecutionTest.returnStatementWorks(CatscriptStatementExecutionTest.java:85)

[ERROR] varInsideFunctionWorksProperly  Time elapsed: 0.001 s  <<< ERROR!
java.lang.IllegalArgumentException: 
Error at instruction 0: Cannot pop operand off an empty stack. foo()I
00000 R .  :  :     INVOKESTATIC java/lang/Integer.valueOf (I)Ljava/lang/Integer;
00001 ?    :     LDC 42
00002 ?    :     ISTORE 1
00003 ?    :     ILOAD 1
00004 ?    :     INVOKESTATIC java/lang/Integer.valueOf (I)Ljava/lang/Integer;
00005 ?    :     IRETURN


	at edu.montana.csci.csci468.bytecode.CatscriptStatementExecutionTest.varInsideFunctionWorksProperly(CatscriptStatementExecutionTest.java:48)
Caused by: org.objectweb.asm.tree.analysis.AnalyzerException: Error at instruction 0: Cannot pop operand off an empty stack.
	at edu.montana.csci.csci468.bytecode.CatscriptStatementExecutionTest.varInsideFunctionWorksProperly(CatscriptStatementExecutionTest.java:48)
Caused by: java.lang.IndexOutOfBoundsException: Cannot pop operand off an empty stack.
	at edu.montana.csci.csci468.bytecode.CatscriptStatementExecutionTest.varInsideFunctionWorksProperly(CatscriptStatementExecutionTest.java:48)

[INFO] Running edu.montana.csci.csci468.bytecode.CatscriptBasicExpressionCompileTest
 JVM Bytecode ===================================

// class version 49.0 (49)
// access flags 0x1
public class edu/montana/csci/csci466/bytecode/CatScriptProgram18 extends edu/montana/csci/csci468/parser/statements/CatScriptProgram {


  // access flags 0x1
  public <init>()V
    ALOAD 0
    INVOKESPECIAL edu/montana/csci/csci468/parser/statements/CatScriptProgram.<init> ()V
    RETURN
    MAXSTACK = 1
    MAXLOCALS = 1

  // access flags 0x1
  public execute()V
    ALOAD 0
    LDC 1
    INVOKESTATIC java/lang/Integer.valueOf (I)Ljava/lang/Integer;
    INVOKESTATIC java/lang/String.valueOf (Ljava/lang/Object;)Ljava/lang/String;
    LDC "a"
    INVOKESTATIC java/lang/String.valueOf (Ljava/lang/Object;)Ljava/lang/String;
    INVOKEVIRTUAL java/lang/String.concat (Ljava/lang/String;)Ljava/lang/String;
    INVOKEVIRTUAL edu/montana/csci/csci468/parser/statements/CatScriptProgram.print (Ljava/lang/Object;)V
    RETURN
    MAXSTACK = 3
    MAXLOCALS = 1
}


 ================================================
 JVM Bytecode ===================================

// class version 49.0 (49)
// access flags 0x1
public class edu/montana/csci/csci466/bytecode/CatScriptProgram19 extends edu/montana/csci/csci468/parser/statements/CatScriptProgram {


  // access flags 0x1
  public <init>()V
    ALOAD 0
    INVOKESPECIAL edu/montana/csci/csci468/parser/statements/CatScriptProgram.<init> ()V
    RETURN
    MAXSTACK = 1
    MAXLOCALS = 1

  // access flags 0x1
  public execute()V
    ALOAD 0
    LDC "a"
    INVOKESTATIC java/lang/String.valueOf (Ljava/lang/Object;)Ljava/lang/String;
    LDC 1
    INVOKESTATIC java/lang/Integer.valueOf (I)Ljava/lang/Integer;
    INVOKESTATIC java/lang/String.valueOf (Ljava/lang/Object;)Ljava/lang/String;
    INVOKEVIRTUAL java/lang/String.concat (Ljava/lang/String;)Ljava/lang/String;
    INVOKEVIRTUAL edu/montana/csci/csci468/parser/statements/CatScriptProgram.print (Ljava/lang/Object;)V
    RETURN
    MAXSTACK = 3
    MAXLOCALS = 1
}


 ================================================
 JVM Bytecode ===================================

// class version 49.0 (49)
// access flags 0x1
public class edu/montana/csci/csci466/bytecode/CatScriptProgram20 extends edu/montana/csci/csci468/parser/statements/CatScriptProgram {


  // access flags 0x1
  public <init>()V
    ALOAD 0
    INVOKESPECIAL edu/montana/csci/csci468/parser/statements/CatScriptProgram.<init> ()V
    RETURN
    MAXSTACK = 1
    MAXLOCALS = 1

  // access flags 0x1
  public execute()V
    ALOAD 0
    ACONST_NULL
    INVOKESTATIC java/lang/String.valueOf (Ljava/lang/Object;)Ljava/lang/String;
    LDC "a"
    INVOKESTATIC java/lang/String.valueOf (Ljava/lang/Object;)Ljava/lang/String;
    INVOKEVIRTUAL java/lang/String.concat (Ljava/lang/String;)Ljava/lang/String;
    INVOKEVIRTUAL edu/montana/csci/csci468/parser/statements/CatScriptProgram.print (Ljava/lang/Object;)V
    RETURN
    MAXSTACK = 3
    MAXLOCALS = 1
}


 ================================================
 JVM Bytecode ===================================

// class version 49.0 (49)
// access flags 0x1
public class edu/montana/csci/csci466/bytecode/CatScriptProgram21 extends edu/montana/csci/csci468/parser/statements/CatScriptProgram {


  // access flags 0x1
  public <init>()V
    ALOAD 0
    INVOKESPECIAL edu/montana/csci/csci468/parser/statements/CatScriptProgram.<init> ()V
    RETURN
    MAXSTACK = 1
    MAXLOCALS = 1

  // access flags 0x1
  public execute()V
    ALOAD 0
    LDC "a"
    INVOKESTATIC java/lang/String.valueOf (Ljava/lang/Object;)Ljava/lang/String;
    ACONST_NULL
    INVOKESTATIC java/lang/String.valueOf (Ljava/lang/Object;)Ljava/lang/String;
    INVOKEVIRTUAL java/lang/String.concat (Ljava/lang/String;)Ljava/lang/String;
    INVOKEVIRTUAL edu/montana/csci/csci468/parser/statements/CatScriptProgram.print (Ljava/lang/Object;)V
    RETURN
    MAXSTACK = 3
    MAXLOCALS = 1
}


 ================================================
 JVM Bytecode ===================================

// class version 49.0 (49)
// access flags 0x1
public class edu/montana/csci/csci466/bytecode/CatScriptProgram22 extends edu/montana/csci/csci468/parser/statements/CatScriptProgram {


  // access flags 0x1
  public <init>()V
    ALOAD 0
    INVOKESPECIAL edu/montana/csci/csci468/parser/statements/CatScriptProgram.<init> ()V
    RETURN
    MAXSTACK = 1
    MAXLOCALS = 1

  // access flags 0x1
  public execute()V
    ALOAD 0
    LDC 1
    INVOKESTATIC java/lang/Integer.valueOf (I)Ljava/lang/Integer;
    INVOKEVIRTUAL edu/montana/csci/csci468/parser/statements/CatScriptProgram.print (Ljava/lang/Object;)V
    RETURN
    MAXSTACK = 2
    MAXLOCALS = 1
}


 ================================================
 JVM Bytecode ===================================

// class version 49.0 (49)
// access flags 0x1
public class edu/montana/csci/csci466/bytecode/CatScriptProgram23 extends edu/montana/csci/csci468/parser/statements/CatScriptProgram {


  // access flags 0x1
  public <init>()V
    ALOAD 0
    INVOKESPECIAL edu/montana/csci/csci468/parser/statements/CatScriptProgram.<init> ()V
    RETURN
    MAXSTACK = 1
    MAXLOCALS = 1

  // access flags 0x1
  public execute()V
    ALOAD 0
    LDC 1
    INVOKESTATIC java/lang/Boolean.valueOf (Z)Ljava/lang/Boolean;
    INVOKEVIRTUAL edu/montana/csci/csci468/parser/statements/CatScriptProgram.print (Ljava/lang/Object;)V
    RETURN
    MAXSTACK = 2
    MAXLOCALS = 1
}


 ================================================
 JVM Bytecode ===================================

// class version 49.0 (49)
// access flags 0x1
public class edu/montana/csci/csci466/bytecode/CatScriptProgram24 extends edu/montana/csci/csci468/parser/statements/CatScriptProgram {


  // access flags 0x1
  public <init>()V
    ALOAD 0
    INVOKESPECIAL edu/montana/csci/csci468/parser/statements/CatScriptProgram.<init> ()V
    RETURN
    MAXSTACK = 1
    MAXLOCALS = 1

  // access flags 0x1
  public execute()V
    ALOAD 0
    ACONST_NULL
    INVOKEVIRTUAL edu/montana/csci/csci468/parser/statements/CatScriptProgram.print (Ljava/lang/Object;)V
    RETURN
    MAXSTACK = 2
    MAXLOCALS = 1
}


 ================================================
 JVM Bytecode ===================================

// class version 49.0 (49)
// access flags 0x1
public class edu/montana/csci/csci466/bytecode/CatScriptProgram25 extends edu/montana/csci/csci468/parser/statements/CatScriptProgram {


  // access flags 0x1
  public <init>()V
    ALOAD 0
    INVOKESPECIAL edu/montana/csci/csci468/parser/statements/CatScriptProgram.<init> ()V
    RETURN
    MAXSTACK = 1
    MAXLOCALS = 1

  // access flags 0x1
  public execute()V
    ALOAD 0
    LDC "asdf"
    INVOKEVIRTUAL edu/montana/csci/csci468/parser/statements/CatScriptProgram.print (Ljava/lang/Object;)V
    RETURN
    MAXSTACK = 2
    MAXLOCALS = 1
}


 ================================================
 JVM Bytecode ===================================

// class version 49.0 (49)
// access flags 0x1
public class edu/montana/csci/csci466/bytecode/CatScriptProgram26 extends edu/montana/csci/csci468/parser/statements/CatScriptProgram {


  // access flags 0x1
  public <init>()V
    ALOAD 0
    INVOKESPECIAL edu/montana/csci/csci468/parser/statements/CatScriptProgram.<init> ()V
    RETURN
    MAXSTACK = 1
    MAXLOCALS = 1

  // access flags 0x1
  public execute()V
    ALOAD 0
    NEW java/util/ArrayList
    DUP
    INVOKESPECIAL java/util/ArrayList.<init> ()V
    DUP
    LDC 1
    INVOKESTATIC java/lang/Integer.valueOf (I)Ljava/lang/Integer;
    INVOKEVIRTUAL java/util/ArrayList.add (Ljava/lang/Object;)Z
    POP
    DUP
    LDC 2
    INVOKESTATIC java/lang/Integer.valueOf (I)Ljava/lang/Integer;
    INVOKEVIRTUAL java/util/ArrayList.add (Ljava/lang/Object;)Z
    POP
    DUP
    LDC 3
    INVOKESTATIC java/lang/Integer.valueOf (I)Ljava/lang/Integer;
    INVOKEVIRTUAL java/util/ArrayList.add (Ljava/lang/Object;)Z
    POP
    INVOKEVIRTUAL edu/montana/csci/csci468/parser/statements/CatScriptProgram.print (Ljava/lang/Object;)V
    RETURN
    MAXSTACK = 4
    MAXLOCALS = 1
}


 ================================================
 JVM Bytecode ===================================

// class version 49.0 (49)
// access flags 0x1
public class edu/montana/csci/csci466/bytecode/CatScriptProgram27 extends edu/montana/csci/csci468/parser/statements/CatScriptProgram {


  // access flags 0x1
  public <init>()V
    ALOAD 0
    INVOKESPECIAL edu/montana/csci/csci468/parser/statements/CatScriptProgram.<init> ()V
    RETURN
    MAXSTACK = 1
    MAXLOCALS = 1

  // access flags 0x1
  public execute()V
    ALOAD 0
    LDC 1
    INEG
    INVOKESTATIC java/lang/Integer.valueOf (I)Ljava/lang/Integer;
    INVOKEVIRTUAL edu/montana/csci/csci468/parser/statements/CatScriptProgram.print (Ljava/lang/Object;)V
    RETURN
    MAXSTACK = 2
    MAXLOCALS = 1
}


 ================================================
 JVM Bytecode ===================================

// class version 49.0 (49)
// access flags 0x1
public class edu/montana/csci/csci466/bytecode/CatScriptProgram28 extends edu/montana/csci/csci468/parser/statements/CatScriptProgram {


  // access flags 0x1
  public <init>()V
    ALOAD 0
    INVOKESPECIAL edu/montana/csci/csci468/parser/statements/CatScriptProgram.<init> ()V
    RETURN
    MAXSTACK = 1
    MAXLOCALS = 1

  // access flags 0x1
  public execute()V
    ALOAD 0
    LDC 1
    IFEQ L0
    LDC 0
    GOTO L1
   L0
   FRAME FULL [edu/montana/csci/csci466/bytecode/CatScriptProgram28] [edu/montana/csci/csci466/bytecode/CatScriptProgram28]
    LDC 1
   L1
   FRAME FULL [edu/montana/csci/csci466/bytecode/CatScriptProgram28] [edu/montana/csci/csci466/bytecode/CatScriptProgram28 I]
    INVOKESTATIC java/lang/Boolean.valueOf (Z)Ljava/lang/Boolean;
    INVOKEVIRTUAL edu/montana/csci/csci468/parser/statements/CatScriptProgram.print (Ljava/lang/Object;)V
    RETURN
    MAXSTACK = 2
    MAXLOCALS = 1
}


 ================================================
 JVM Bytecode ===================================

// class version 49.0 (49)
// access flags 0x1
public class edu/montana/csci/csci466/bytecode/CatScriptProgram29 extends edu/montana/csci/csci468/parser/statements/CatScriptProgram {


  // access flags 0x1
  public <init>()V
    ALOAD 0
    INVOKESPECIAL edu/montana/csci/csci468/parser/statements/CatScriptProgram.<init> ()V
    RETURN
    MAXSTACK = 1
    MAXLOCALS = 1

  // access flags 0x1
  public execute()V
    ALOAD 0
    LDC 1
    INVOKESTATIC java/lang/Integer.valueOf (I)Ljava/lang/Integer;
    INVOKEVIRTUAL edu/montana/csci/csci468/parser/statements/CatScriptProgram.print (Ljava/lang/Object;)V
    RETURN
    MAXSTACK = 2
    MAXLOCALS = 1
}


 ================================================
 JVM Bytecode ===================================

// class version 49.0 (49)
// access flags 0x1
public class edu/montana/csci/csci466/bytecode/CatScriptProgram30 extends edu/montana/csci/csci468/parser/statements/CatScriptProgram {


  // access flags 0x1
  public <init>()V
    ALOAD 0
    INVOKESPECIAL edu/montana/csci/csci468/parser/statements/CatScriptProgram.<init> ()V
    RETURN
    MAXSTACK = 1
    MAXLOCALS = 1

  // access flags 0x1
  public execute()V
    ALOAD 0
    LDC 1
    LDC 1
    IADD
    INVOKESTATIC java/lang/Integer.valueOf (I)Ljava/lang/Integer;
    INVOKEVIRTUAL edu/montana/csci/csci468/parser/statements/CatScriptProgram.print (Ljava/lang/Object;)V
    RETURN
    MAXSTACK = 3
    MAXLOCALS = 1
}


 ================================================
 JVM Bytecode ===================================

// class version 49.0 (49)
// access flags 0x1
public class edu/montana/csci/csci466/bytecode/CatScriptProgram31 extends edu/montana/csci/csci468/parser/statements/CatScriptProgram {


  // access flags 0x1
  public <init>()V
    ALOAD 0
    INVOKESPECIAL edu/montana/csci/csci468/parser/statements/CatScriptProgram.<init> ()V
    RETURN
    MAXSTACK = 1
    MAXLOCALS = 1

  // access flags 0x1
  public execute()V
    ALOAD 0
    LDC 1
    LDC 1
    ISUB
    INVOKESTATIC java/lang/Integer.valueOf (I)Ljava/lang/Integer;
    INVOKEVIRTUAL edu/montana/csci/csci468/parser/statements/CatScriptProgram.print (Ljava/lang/Object;)V
    RETURN
    MAXSTACK = 3
    MAXLOCALS = 1
}


 ================================================
 JVM Bytecode ===================================

// class version 49.0 (49)
// access flags 0x1
public class edu/montana/csci/csci466/bytecode/CatScriptProgram32 extends edu/montana/csci/csci468/parser/statements/CatScriptProgram {


  // access flags 0x1
  public <init>()V
    ALOAD 0
    INVOKESPECIAL edu/montana/csci/csci468/parser/statements/CatScriptProgram.<init> ()V
    RETURN
    MAXSTACK = 1
    MAXLOCALS = 1

  // access flags 0x1
  public execute()V
    ALOAD 0
    LDC 1
    LDC 2
    ISUB
    LDC 1
    ISUB
    INVOKESTATIC java/lang/Integer.valueOf (I)Ljava/lang/Integer;
    INVOKEVIRTUAL edu/montana/csci/csci468/parser/statements/CatScriptProgram.print (Ljava/lang/Object;)V
    RETURN
    MAXSTACK = 3
    MAXLOCALS = 1
}


 ================================================
 JVM Bytecode ===================================

// class version 49.0 (49)
// access flags 0x1
public class edu/montana/csci/csci466/bytecode/CatScriptProgram33 extends edu/montana/csci/csci468/parser/statements/CatScriptProgram {


  // access flags 0x1
  public <init>()V
    ALOAD 0
    INVOKESPECIAL edu/montana/csci/csci468/parser/statements/CatScriptProgram.<init> ()V
    RETURN
    MAXSTACK = 1
    MAXLOCALS = 1

  // access flags 0x1
  public execute()V
    ALOAD 0
    LDC 1
    LDC 2
    IMUL
    INVOKESTATIC java/lang/Integer.valueOf (I)Ljava/lang/Integer;
    INVOKEVIRTUAL edu/montana/csci/csci468/parser/statements/CatScriptProgram.print (Ljava/lang/Object;)V
    RETURN
    MAXSTACK = 3
    MAXLOCALS = 1
}


 ================================================
 JVM Bytecode ===================================

// class version 49.0 (49)
// access flags 0x1
public class edu/montana/csci/csci466/bytecode/CatScriptProgram34 extends edu/montana/csci/csci468/parser/statements/CatScriptProgram {


  // access flags 0x1
  public <init>()V
    ALOAD 0
    INVOKESPECIAL edu/montana/csci/csci468/parser/statements/CatScriptProgram.<init> ()V
    RETURN
    MAXSTACK = 1
    MAXLOCALS = 1

  // access flags 0x1
  public execute()V
    ALOAD 0
    LDC 8
    LDC 2
    IDIV
    INVOKESTATIC java/lang/Integer.valueOf (I)Ljava/lang/Integer;
    INVOKEVIRTUAL edu/montana/csci/csci468/parser/statements/CatScriptProgram.print (Ljava/lang/Object;)V
    RETURN
    MAXSTACK = 3
    MAXLOCALS = 1
}


 ================================================
 JVM Bytecode ===================================

// class version 49.0 (49)
// access flags 0x1
public class edu/montana/csci/csci466/bytecode/CatScriptProgram35 extends edu/montana/csci/csci468/parser/statements/CatScriptProgram {


  // access flags 0x1
  public <init>()V
    ALOAD 0
    INVOKESPECIAL edu/montana/csci/csci468/parser/statements/CatScriptProgram.<init> ()V
    RETURN
    MAXSTACK = 1
    MAXLOCALS = 1

  // access flags 0x1
  public execute()V
    ALOAD 0
    LDC 2
    LDC 4
    IMUL
    LDC 2
    IDIV
    INVOKESTATIC java/lang/Integer.valueOf (I)Ljava/lang/Integer;
    INVOKEVIRTUAL edu/montana/csci/csci468/parser/statements/CatScriptProgram.print (Ljava/lang/Object;)V
    RETURN
    MAXSTACK = 3
    MAXLOCALS = 1
}


 ================================================
 JVM Bytecode ===================================

// class version 49.0 (49)
// access flags 0x1
public class edu/montana/csci/csci466/bytecode/CatScriptProgram36 extends edu/montana/csci/csci468/parser/statements/CatScriptProgram {


  // access flags 0x1
  public <init>()V
    ALOAD 0
    INVOKESPECIAL edu/montana/csci/csci468/parser/statements/CatScriptProgram.<init> ()V
    RETURN
    MAXSTACK = 1
    MAXLOCALS = 1

  // access flags 0x1
  public execute()V
    ALOAD 0
    LDC 1
    LDC 1
    IF_ICMPEQ L0
    LDC 0
    GOTO L1
   L0
   FRAME FULL [edu/montana/csci/csci466/bytecode/CatScriptProgram36] [edu/montana/csci/csci466/bytecode/CatScriptProgram36]
    LDC 1
   L1
   FRAME FULL [edu/montana/csci/csci466/bytecode/CatScriptProgram36] [edu/montana/csci/csci466/bytecode/CatScriptProgram36 I]
    INVOKESTATIC java/lang/Boolean.valueOf (Z)Ljava/lang/Boolean;
    INVOKEVIRTUAL edu/montana/csci/csci468/parser/statements/CatScriptProgram.print (Ljava/lang/Object;)V
    RETURN
    MAXSTACK = 3
    MAXLOCALS = 1
}


 ================================================
 JVM Bytecode ===================================

// class version 49.0 (49)
// access flags 0x1
public class edu/montana/csci/csci466/bytecode/CatScriptProgram37 extends edu/montana/csci/csci468/parser/statements/CatScriptProgram {


  // access flags 0x1
  public <init>()V
    ALOAD 0
    INVOKESPECIAL edu/montana/csci/csci468/parser/statements/CatScriptProgram.<init> ()V
    RETURN
    MAXSTACK = 1
    MAXLOCALS = 1

  // access flags 0x1
  public execute()V
    ALOAD 0
    LDC 1
    LDC 1
    IF_ICMPEQ L0
    LDC 0
    GOTO L1
   L0
   FRAME FULL [edu/montana/csci/csci466/bytecode/CatScriptProgram37] [edu/montana/csci/csci466/bytecode/CatScriptProgram37]
    LDC 1
   L1
   FRAME FULL [edu/montana/csci/csci466/bytecode/CatScriptProgram37] [edu/montana/csci/csci466/bytecode/CatScriptProgram37 I]
    INVOKESTATIC java/lang/Boolean.valueOf (Z)Ljava/lang/Boolean;
    INVOKEVIRTUAL edu/montana/csci/csci468/parser/statements/CatScriptProgram.print (Ljava/lang/Object;)V
    RETURN
    MAXSTACK = 3
    MAXLOCALS = 1
}


 ================================================
 JVM Bytecode ===================================

// class version 49.0 (49)
// access flags 0x1
public class edu/montana/csci/csci466/bytecode/CatScriptProgram38 extends edu/montana/csci/csci468/parser/statements/CatScriptProgram {


  // access flags 0x1
  public <init>()V
    ALOAD 0
    INVOKESPECIAL edu/montana/csci/csci468/parser/statements/CatScriptProgram.<init> ()V
    RETURN
    MAXSTACK = 1
    MAXLOCALS = 1

  // access flags 0x1
  public execute()V
    ALOAD 0
    ACONST_NULL
    ACONST_NULL
    IF_ACMPEQ L0
    LDC 0
    GOTO L1
   L0
   FRAME FULL [edu/montana/csci/csci466/bytecode/CatScriptProgram38] [edu/montana/csci/csci466/bytecode/CatScriptProgram38]
    LDC 1
   L1
   FRAME FULL [edu/montana/csci/csci466/bytecode/CatScriptProgram38] [edu/montana/csci/csci466/bytecode/CatScriptProgram38 I]
    INVOKESTATIC java/lang/Boolean.valueOf (Z)Ljava/lang/Boolean;
    INVOKEVIRTUAL edu/montana/csci/csci468/parser/statements/CatScriptProgram.print (Ljava/lang/Object;)V
    RETURN
    MAXSTACK = 3
    MAXLOCALS = 1
}


 ================================================
 JVM Bytecode ===================================

// class version 49.0 (49)
// access flags 0x1
public class edu/montana/csci/csci466/bytecode/CatScriptProgram39 extends edu/montana/csci/csci468/parser/statements/CatScriptProgram {


  // access flags 0x1
  public <init>()V
    ALOAD 0
    INVOKESPECIAL edu/montana/csci/csci468/parser/statements/CatScriptProgram.<init> ()V
    RETURN
    MAXSTACK = 1
    MAXLOCALS = 1

  // access flags 0x1
  public execute()V
    ALOAD 0
    ACONST_NULL
    ACONST_NULL
    IF_ACMPEQ L0
    LDC 0
    GOTO L1
   L0
   FRAME FULL [edu/montana/csci/csci466/bytecode/CatScriptProgram39] [edu/montana/csci/csci466/bytecode/CatScriptProgram39]
    LDC 1
   L1
   FRAME FULL [edu/montana/csci/csci466/bytecode/CatScriptProgram39] [edu/montana/csci/csci466/bytecode/CatScriptProgram39 I]
    INVOKESTATIC java/lang/Boolean.valueOf (Z)Ljava/lang/Boolean;
    INVOKEVIRTUAL edu/montana/csci/csci468/parser/statements/CatScriptProgram.print (Ljava/lang/Object;)V
    RETURN
    MAXSTACK = 3
    MAXLOCALS = 1
}


 ================================================
 JVM Bytecode ===================================

// class version 49.0 (49)
// access flags 0x1
public class edu/montana/csci/csci466/bytecode/CatScriptProgram40 extends edu/montana/csci/csci468/parser/statements/CatScriptProgram {


  // access flags 0x1
  public <init>()V
    ALOAD 0
    INVOKESPECIAL edu/montana/csci/csci468/parser/statements/CatScriptProgram.<init> ()V
    RETURN
    MAXSTACK = 1
    MAXLOCALS = 1

  // access flags 0x1
  public execute()V
    ALOAD 0
    LDC 1
    LDC 1
    IF_ICMPEQ L0
    LDC 0
    GOTO L1
   L0
   FRAME FULL [edu/montana/csci/csci466/bytecode/CatScriptProgram40] [edu/montana/csci/csci466/bytecode/CatScriptProgram40]
    LDC 1
   L1
   FRAME FULL [edu/montana/csci/csci466/bytecode/CatScriptProgram40] [edu/montana/csci/csci466/bytecode/CatScriptProgram40 I]
    INVOKESTATIC java/lang/Boolean.valueOf (Z)Ljava/lang/Boolean;
    INVOKEVIRTUAL edu/montana/csci/csci468/parser/statements/CatScriptProgram.print (Ljava/lang/Object;)V
    RETURN
    MAXSTACK = 3
    MAXLOCALS = 1
}


 ================================================
 JVM Bytecode ===================================

// class version 49.0 (49)
// access flags 0x1
public class edu/montana/csci/csci466/bytecode/CatScriptProgram41 extends edu/montana/csci/csci468/parser/statements/CatScriptProgram {


  // access flags 0x1
  public <init>()V
    ALOAD 0
    INVOKESPECIAL edu/montana/csci/csci468/parser/statements/CatScriptProgram.<init> ()V
    RETURN
    MAXSTACK = 1
    MAXLOCALS = 1

  // access flags 0x1
  public execute()V
    ALOAD 0
    LDC 1
    LDC 2
    IF_ICMPGT L0
    LDC 0
    GOTO L1
   L0
   FRAME FULL [edu/montana/csci/csci466/bytecode/CatScriptProgram41] [edu/montana/csci/csci466/bytecode/CatScriptProgram41]
    LDC 1
   L1
   FRAME FULL [edu/montana/csci/csci466/bytecode/CatScriptProgram41] [edu/montana/csci/csci466/bytecode/CatScriptProgram41 I]
    INVOKESTATIC java/lang/Boolean.valueOf (Z)Ljava/lang/Boolean;
    INVOKEVIRTUAL edu/montana/csci/csci468/parser/statements/CatScriptProgram.print (Ljava/lang/Object;)V
    RETURN
    MAXSTACK = 3
    MAXLOCALS = 1
}


 ================================================
 JVM Bytecode ===================================

// class version 49.0 (49)
// access flags 0x1
public class edu/montana/csci/csci466/bytecode/CatScriptProgram42 extends edu/montana/csci/csci468/parser/statements/CatScriptProgram {


  // access flags 0x1
  public <init>()V
    ALOAD 0
    INVOKESPECIAL edu/montana/csci/csci468/parser/statements/CatScriptProgram.<init> ()V
    RETURN
    MAXSTACK = 1
    MAXLOCALS = 1

  // access flags 0x1
  public execute()V
    ALOAD 0
    LDC 1
    LDC 2
    IF_ICMPGE L0
    LDC 0
    GOTO L1
   L0
   FRAME FULL [edu/montana/csci/csci466/bytecode/CatScriptProgram42] [edu/montana/csci/csci466/bytecode/CatScriptProgram42]
    LDC 1
   L1
   FRAME FULL [edu/montana/csci/csci466/bytecode/CatScriptProgram42] [edu/montana/csci/csci466/bytecode/CatScriptProgram42 I]
    INVOKESTATIC java/lang/Boolean.valueOf (Z)Ljava/lang/Boolean;
    INVOKEVIRTUAL edu/montana/csci/csci468/parser/statements/CatScriptProgram.print (Ljava/lang/Object;)V
    RETURN
    MAXSTACK = 3
    MAXLOCALS = 1
}


 ================================================
 JVM Bytecode ===================================

// class version 49.0 (49)
// access flags 0x1
public class edu/montana/csci/csci466/bytecode/CatScriptProgram43 extends edu/montana/csci/csci468/parser/statements/CatScriptProgram {


  // access flags 0x1
  public <init>()V
    ALOAD 0
    INVOKESPECIAL edu/montana/csci/csci468/parser/statements/CatScriptProgram.<init> ()V
    RETURN
    MAXSTACK = 1
    MAXLOCALS = 1

  // access flags 0x1
  public execute()V
    ALOAD 0
    LDC 1
    LDC 2
    IF_ICMPLE L0
    LDC 0
    GOTO L1
   L0
   FRAME FULL [edu/montana/csci/csci466/bytecode/CatScriptProgram43] [edu/montana/csci/csci466/bytecode/CatScriptProgram43]
    LDC 1
   L1
   FRAME FULL [edu/montana/csci/csci466/bytecode/CatScriptProgram43] [edu/montana/csci/csci466/bytecode/CatScriptProgram43 I]
    INVOKESTATIC java/lang/Boolean.valueOf (Z)Ljava/lang/Boolean;
    INVOKEVIRTUAL edu/montana/csci/csci468/parser/statements/CatScriptProgram.print (Ljava/lang/Object;)V
    RETURN
    MAXSTACK = 3
    MAXLOCALS = 1
}


 ================================================
 JVM Bytecode ===================================

// class version 49.0 (49)
// access flags 0x1
public class edu/montana/csci/csci466/bytecode/CatScriptProgram44 extends edu/montana/csci/csci468/parser/statements/CatScriptProgram {


  // access flags 0x1
  public <init>()V
    ALOAD 0
    INVOKESPECIAL edu/montana/csci/csci468/parser/statements/CatScriptProgram.<init> ()V
    RETURN
    MAXSTACK = 1
    MAXLOCALS = 1

  // access flags 0x1
  public execute()V
    ALOAD 0
    LDC 1
    LDC 2
    IF_ICMPLT L0
    LDC 0
    GOTO L1
   L0
   FRAME FULL [edu/montana/csci/csci466/bytecode/CatScriptProgram44] [edu/montana/csci/csci466/bytecode/CatScriptProgram44]
    LDC 1
   L1
   FRAME FULL [edu/montana/csci/csci466/bytecode/CatScriptProgram44] [edu/montana/csci/csci466/bytecode/CatScriptProgram44 I]
    INVOKESTATIC java/lang/Boolean.valueOf (Z)Ljava/lang/Boolean;
    INVOKEVIRTUAL edu/montana/csci/csci468/parser/statements/CatScriptProgram.print (Ljava/lang/Object;)V
    RETURN
    MAXSTACK = 3
    MAXLOCALS = 1
}


 ================================================
 JVM Bytecode ===================================

// class version 49.0 (49)
// access flags 0x1
public class edu/montana/csci/csci466/bytecode/CatScriptProgram45 extends edu/montana/csci/csci468/parser/statements/CatScriptProgram {


  // access flags 0x1
  public <init>()V
    ALOAD 0
    INVOKESPECIAL edu/montana/csci/csci468/parser/statements/CatScriptProgram.<init> ()V
    RETURN
    MAXSTACK = 1
    MAXLOCALS = 1

  // access flags 0x1
  public execute()V
    ALOAD 0
    LDC 2
    LDC 1
    IF_ICMPGT L0
    LDC 0
    GOTO L1
   L0
   FRAME FULL [edu/montana/csci/csci466/bytecode/CatScriptProgram45] [edu/montana/csci/csci466/bytecode/CatScriptProgram45]
    LDC 1
   L1
   FRAME FULL [edu/montana/csci/csci466/bytecode/CatScriptProgram45] [edu/montana/csci/csci466/bytecode/CatScriptProgram45 I]
    INVOKESTATIC java/lang/Boolean.valueOf (Z)Ljava/lang/Boolean;
    INVOKEVIRTUAL edu/montana/csci/csci468/parser/statements/CatScriptProgram.print (Ljava/lang/Object;)V
    RETURN
    MAXSTACK = 3
    MAXLOCALS = 1
}


 ================================================
 JVM Bytecode ===================================

// class version 49.0 (49)
// access flags 0x1
public class edu/montana/csci/csci466/bytecode/CatScriptProgram46 extends edu/montana/csci/csci468/parser/statements/CatScriptProgram {


  // access flags 0x1
  public <init>()V
    ALOAD 0
    INVOKESPECIAL edu/montana/csci/csci468/parser/statements/CatScriptProgram.<init> ()V
    RETURN
    MAXSTACK = 1
    MAXLOCALS = 1

  // access flags 0x1
  public execute()V
    ALOAD 0
    LDC 2
    LDC 1
    IF_ICMPGE L0
    LDC 0
    GOTO L1
   L0
   FRAME FULL [edu/montana/csci/csci466/bytecode/CatScriptProgram46] [edu/montana/csci/csci466/bytecode/CatScriptProgram46]
    LDC 1
   L1
   FRAME FULL [edu/montana/csci/csci466/bytecode/CatScriptProgram46] [edu/montana/csci/csci466/bytecode/CatScriptProgram46 I]
    INVOKESTATIC java/lang/Boolean.valueOf (Z)Ljava/lang/Boolean;
    INVOKEVIRTUAL edu/montana/csci/csci468/parser/statements/CatScriptProgram.print (Ljava/lang/Object;)V
    RETURN
    MAXSTACK = 3
    MAXLOCALS = 1
}


 ================================================
 JVM Bytecode ===================================

// class version 49.0 (49)
// access flags 0x1
public class edu/montana/csci/csci466/bytecode/CatScriptProgram47 extends edu/montana/csci/csci468/parser/statements/CatScriptProgram {


  // access flags 0x1
  public <init>()V
    ALOAD 0
    INVOKESPECIAL edu/montana/csci/csci468/parser/statements/CatScriptProgram.<init> ()V
    RETURN
    MAXSTACK = 1
    MAXLOCALS = 1

  // access flags 0x1
  public execute()V
    ALOAD 0
    LDC 2
    LDC 1
    IF_ICMPLE L0
    LDC 0
    GOTO L1
   L0
   FRAME FULL [edu/montana/csci/csci466/bytecode/CatScriptProgram47] [edu/montana/csci/csci466/bytecode/CatScriptProgram47]
    LDC 1
   L1
   FRAME FULL [edu/montana/csci/csci466/bytecode/CatScriptProgram47] [edu/montana/csci/csci466/bytecode/CatScriptProgram47 I]
    INVOKESTATIC java/lang/Boolean.valueOf (Z)Ljava/lang/Boolean;
    INVOKEVIRTUAL edu/montana/csci/csci468/parser/statements/CatScriptProgram.print (Ljava/lang/Object;)V
    RETURN
    MAXSTACK = 3
    MAXLOCALS = 1
}


 ================================================
 JVM Bytecode ===================================

// class version 49.0 (49)
// access flags 0x1
public class edu/montana/csci/csci466/bytecode/CatScriptProgram48 extends edu/montana/csci/csci468/parser/statements/CatScriptProgram {


  // access flags 0x1
  public <init>()V
    ALOAD 0
    INVOKESPECIAL edu/montana/csci/csci468/parser/statements/CatScriptProgram.<init> ()V
    RETURN
    MAXSTACK = 1
    MAXLOCALS = 1

  // access flags 0x1
  public execute()V
    ALOAD 0
    LDC 2
    LDC 1
    IF_ICMPLT L0
    LDC 0
    GOTO L1
   L0
   FRAME FULL [edu/montana/csci/csci466/bytecode/CatScriptProgram48] [edu/montana/csci/csci466/bytecode/CatScriptProgram48]
    LDC 1
   L1
   FRAME FULL [edu/montana/csci/csci466/bytecode/CatScriptProgram48] [edu/montana/csci/csci466/bytecode/CatScriptProgram48 I]
    INVOKESTATIC java/lang/Boolean.valueOf (Z)Ljava/lang/Boolean;
    INVOKEVIRTUAL edu/montana/csci/csci468/parser/statements/CatScriptProgram.print (Ljava/lang/Object;)V
    RETURN
    MAXSTACK = 3
    MAXLOCALS = 1
}


 ================================================
 JVM Bytecode ===================================

// class version 49.0 (49)
// access flags 0x1
public class edu/montana/csci/csci466/bytecode/CatScriptProgram49 extends edu/montana/csci/csci468/parser/statements/CatScriptProgram {


  // access flags 0x1
  public <init>()V
    ALOAD 0
    INVOKESPECIAL edu/montana/csci/csci468/parser/statements/CatScriptProgram.<init> ()V
    RETURN
    MAXSTACK = 1
    MAXLOCALS = 1

  // access flags 0x1
  public execute()V
    ALOAD 0
    LDC 1
    LDC 1
    IF_ICMPGT L0
    LDC 0
    GOTO L1
   L0
   FRAME FULL [edu/montana/csci/csci466/bytecode/CatScriptProgram49] [edu/montana/csci/csci466/bytecode/CatScriptProgram49]
    LDC 1
   L1
   FRAME FULL [edu/montana/csci/csci466/bytecode/CatScriptProgram49] [edu/montana/csci/csci466/bytecode/CatScriptProgram49 I]
    INVOKESTATIC java/lang/Boolean.valueOf (Z)Ljava/lang/Boolean;
    INVOKEVIRTUAL edu/montana/csci/csci468/parser/statements/CatScriptProgram.print (Ljava/lang/Object;)V
    RETURN
    MAXSTACK = 3
    MAXLOCALS = 1
}


 ================================================
 JVM Bytecode ===================================

// class version 49.0 (49)
// access flags 0x1
public class edu/montana/csci/csci466/bytecode/CatScriptProgram50 extends edu/montana/csci/csci468/parser/statements/CatScriptProgram {


  // access flags 0x1
  public <init>()V
    ALOAD 0
    INVOKESPECIAL edu/montana/csci/csci468/parser/statements/CatScriptProgram.<init> ()V
    RETURN
    MAXSTACK = 1
    MAXLOCALS = 1

  // access flags 0x1
  public execute()V
    ALOAD 0
    LDC 1
    LDC 1
    IF_ICMPGE L0
    LDC 0
    GOTO L1
   L0
   FRAME FULL [edu/montana/csci/csci466/bytecode/CatScriptProgram50] [edu/montana/csci/csci466/bytecode/CatScriptProgram50]
    LDC 1
   L1
   FRAME FULL [edu/montana/csci/csci466/bytecode/CatScriptProgram50] [edu/montana/csci/csci466/bytecode/CatScriptProgram50 I]
    INVOKESTATIC java/lang/Boolean.valueOf (Z)Ljava/lang/Boolean;
    INVOKEVIRTUAL edu/montana/csci/csci468/parser/statements/CatScriptProgram.print (Ljava/lang/Object;)V
    RETURN
    MAXSTACK = 3
    MAXLOCALS = 1
}


 ================================================
 JVM Bytecode ===================================

// class version 49.0 (49)
// access flags 0x1
public class edu/montana/csci/csci466/bytecode/CatScriptProgram51 extends edu/montana/csci/csci468/parser/statements/CatScriptProgram {


  // access flags 0x1
  public <init>()V
    ALOAD 0
    INVOKESPECIAL edu/montana/csci/csci468/parser/statements/CatScriptProgram.<init> ()V
    RETURN
    MAXSTACK = 1
    MAXLOCALS = 1

  // access flags 0x1
  public execute()V
    ALOAD 0
    LDC 1
    LDC 1
    IF_ICMPLE L0
    LDC 0
    GOTO L1
   L0
   FRAME FULL [edu/montana/csci/csci466/bytecode/CatScriptProgram51] [edu/montana/csci/csci466/bytecode/CatScriptProgram51]
    LDC 1
   L1
   FRAME FULL [edu/montana/csci/csci466/bytecode/CatScriptProgram51] [edu/montana/csci/csci466/bytecode/CatScriptProgram51 I]
    INVOKESTATIC java/lang/Boolean.valueOf (Z)Ljava/lang/Boolean;
    INVOKEVIRTUAL edu/montana/csci/csci468/parser/statements/CatScriptProgram.print (Ljava/lang/Object;)V
    RETURN
    MAXSTACK = 3
    MAXLOCALS = 1
}


 ================================================
 JVM Bytecode ===================================

// class version 49.0 (49)
// access flags 0x1
public class edu/montana/csci/csci466/bytecode/CatScriptProgram52 extends edu/montana/csci/csci468/parser/statements/CatScriptProgram {


  // access flags 0x1
  public <init>()V
    ALOAD 0
    INVOKESPECIAL edu/montana/csci/csci468/parser/statements/CatScriptProgram.<init> ()V
    RETURN
    MAXSTACK = 1
    MAXLOCALS = 1

  // access flags 0x1
  public execute()V
    ALOAD 0
    LDC 2
    LDC 1
    IF_ICMPLT L0
    LDC 0
    GOTO L1
   L0
   FRAME FULL [edu/montana/csci/csci466/bytecode/CatScriptProgram52] [edu/montana/csci/csci466/bytecode/CatScriptProgram52]
    LDC 1
   L1
   FRAME FULL [edu/montana/csci/csci466/bytecode/CatScriptProgram52] [edu/montana/csci/csci466/bytecode/CatScriptProgram52 I]
    INVOKESTATIC java/lang/Boolean.valueOf (Z)Ljava/lang/Boolean;
    INVOKEVIRTUAL edu/montana/csci/csci468/parser/statements/CatScriptProgram.print (Ljava/lang/Object;)V
    RETURN
    MAXSTACK = 3
    MAXLOCALS = 1
}


 ================================================
[INFO] Tests run: 8, Failures: 0, Errors: 0, Skipped: 0, Time elapsed: 0.016 s - in edu.montana.csci.csci468.bytecode.CatscriptBasicExpressionCompileTest
[INFO] Running edu.montana.csci.csci468.bytecode.CatscriptFunctionArgsAndReturnCompileTest
functionDefStatement
IdentifierExpression
IE list<int><int>
funcCallEx
 JVM Bytecode ===================================

// class version 49.0 (49)
// access flags 0x1
public class edu/montana/csci/csci466/bytecode/CatScriptProgram53 extends edu/montana/csci/csci468/parser/statements/CatScriptProgram {


  // access flags 0x1
  public <init>()V
    ALOAD 0
    INVOKESPECIAL edu/montana/csci/csci468/parser/statements/CatScriptProgram.<init> ()V
    RETURN
    MAXSTACK = 1
    MAXLOCALS = 1

  // access flags 0x1
  public execute()V
    ALOAD 0
    NEW java/util/ArrayList
    DUP
    INVOKESPECIAL java/util/ArrayList.<init> ()V
    DUP
    LDC 1
    INVOKESTATIC java/lang/Integer.valueOf (I)Ljava/lang/Integer;
    INVOKEVIRTUAL java/util/ArrayList.add (Ljava/lang/Object;)Z
    POP
    DUP
    LDC 2
    INVOKESTATIC java/lang/Integer.valueOf (I)Ljava/lang/Integer;
    INVOKEVIRTUAL java/util/ArrayList.add (Ljava/lang/Object;)Z
    POP
    DUP
    LDC 3
    INVOKESTATIC java/lang/Integer.valueOf (I)Ljava/lang/Integer;
    INVOKEVIRTUAL java/util/ArrayList.add (Ljava/lang/Object;)Z
    POP
    INVOKEVIRTUAL edu/montana/csci/csci466/bytecode/CatScriptProgram53.foo (Ljava/lang/Object;)V
    RETURN
    MAXSTACK = 4
    MAXLOCALS = 1

  // access flags 0x1
  public foo(Ljava/lang/Object;)V
    ALOAD 0
    ALOAD 1
    INVOKEVIRTUAL edu/montana/csci/csci466/bytecode/CatScriptProgram53.print (Ljava/lang/Object;)V
    RETURN
    MAXSTACK = 2
    MAXLOCALS = 2
}


 ================================================
functionDefStatement
IdentifierExpression
IE string
funcCallEx
 JVM Bytecode ===================================

// class version 49.0 (49)
// access flags 0x1
public class edu/montana/csci/csci466/bytecode/CatScriptProgram54 extends edu/montana/csci/csci468/parser/statements/CatScriptProgram {


  // access flags 0x1
  public <init>()V
    ALOAD 0
    INVOKESPECIAL edu/montana/csci/csci468/parser/statements/CatScriptProgram.<init> ()V
    RETURN
    MAXSTACK = 1
    MAXLOCALS = 1

  // access flags 0x1
  public execute()V
    ALOAD 0
    LDC "foo"
    INVOKEVIRTUAL edu/montana/csci/csci466/bytecode/CatScriptProgram54.foo (Ljava/lang/Object;)V
    RETURN
    MAXSTACK = 2
    MAXLOCALS = 1

  // access flags 0x1
  public foo(Ljava/lang/Object;)V
    ALOAD 0
    ALOAD 1
    INVOKEVIRTUAL edu/montana/csci/csci466/bytecode/CatScriptProgram54.print (Ljava/lang/Object;)V
    RETURN
    MAXSTACK = 2
    MAXLOCALS = 2
}


 ================================================
functionDefStatement
IdentifierExpression
IE object
funcCallEx
 JVM Bytecode ===================================

// class version 49.0 (49)
// access flags 0x1
public class edu/montana/csci/csci466/bytecode/CatScriptProgram55 extends edu/montana/csci/csci468/parser/statements/CatScriptProgram {


  // access flags 0x1
  public <init>()V
    ALOAD 0
    INVOKESPECIAL edu/montana/csci/csci468/parser/statements/CatScriptProgram.<init> ()V
    RETURN
    MAXSTACK = 1
    MAXLOCALS = 1

  // access flags 0x1
  public execute()V
    ALOAD 0
    LDC 1
    INVOKESTATIC java/lang/Integer.valueOf (I)Ljava/lang/Integer;
    INVOKEVIRTUAL edu/montana/csci/csci466/bytecode/CatScriptProgram55.foo (Ljava/lang/Object;)V
    RETURN
    MAXSTACK = 2
    MAXLOCALS = 1

  // access flags 0x1
  public foo(Ljava/lang/Object;)V
    ALOAD 0
    ALOAD 1
    INVOKEVIRTUAL edu/montana/csci/csci466/bytecode/CatScriptProgram55.print (Ljava/lang/Object;)V
    RETURN
    MAXSTACK = 2
    MAXLOCALS = 2
}


 ================================================
functionDefStatement
IdentifierExpression
IE object
funcCallEx
 JVM Bytecode ===================================

// class version 49.0 (49)
// access flags 0x1
public class edu/montana/csci/csci466/bytecode/CatScriptProgram56 extends edu/montana/csci/csci468/parser/statements/CatScriptProgram {


  // access flags 0x1
  public <init>()V
    ALOAD 0
    INVOKESPECIAL edu/montana/csci/csci468/parser/statements/CatScriptProgram.<init> ()V
    RETURN
    MAXSTACK = 1
    MAXLOCALS = 1

  // access flags 0x1
  public execute()V
    ALOAD 0
    LDC 1
    INVOKESTATIC java/lang/Integer.valueOf (I)Ljava/lang/Integer;
    LDC 2
    INVOKESTATIC java/lang/Integer.valueOf (I)Ljava/lang/Integer;
    LDC 3
    INVOKESTATIC java/lang/Integer.valueOf (I)Ljava/lang/Integer;
    INVOKEVIRTUAL edu/montana/csci/csci466/bytecode/CatScriptProgram56.foo (Ljava/lang/Object;Ljava/lang/Object;Ljava/lang/Object;)V
    RETURN
    MAXSTACK = 4
    MAXLOCALS = 1

  // access flags 0x1
  public foo(Ljava/lang/Object;Ljava/lang/Object;Ljava/lang/Object;)V
    ALOAD 0
    ALOAD 1
    INVOKEVIRTUAL edu/montana/csci/csci466/bytecode/CatScriptProgram56.print (Ljava/lang/Object;)V
    RETURN
    MAXSTACK = 2
    MAXLOCALS = 4
}


 ================================================
functionDefStatement
IdentifierExpression
IE object
funcCallEx
 JVM Bytecode ===================================

// class version 49.0 (49)
// access flags 0x1
public class edu/montana/csci/csci466/bytecode/CatScriptProgram57 extends edu/montana/csci/csci468/parser/statements/CatScriptProgram {


  // access flags 0x1
  public <init>()V
    ALOAD 0
    INVOKESPECIAL edu/montana/csci/csci468/parser/statements/CatScriptProgram.<init> ()V
    RETURN
    MAXSTACK = 1
    MAXLOCALS = 1

  // access flags 0x1
  public execute()V
    ALOAD 0
    LDC 1
    INVOKESTATIC java/lang/Integer.valueOf (I)Ljava/lang/Integer;
    LDC 2
    INVOKESTATIC java/lang/Integer.valueOf (I)Ljava/lang/Integer;
    LDC 3
    INVOKESTATIC java/lang/Integer.valueOf (I)Ljava/lang/Integer;
    INVOKEVIRTUAL edu/montana/csci/csci466/bytecode/CatScriptProgram57.foo (Ljava/lang/Object;Ljava/lang/Object;Ljava/lang/Object;)V
    RETURN
    MAXSTACK = 4
    MAXLOCALS = 1

  // access flags 0x1
  public foo(Ljava/lang/Object;Ljava/lang/Object;Ljava/lang/Object;)V
    ALOAD 0
    ALOAD 2
    INVOKEVIRTUAL edu/montana/csci/csci466/bytecode/CatScriptProgram57.print (Ljava/lang/Object;)V
    RETURN
    MAXSTACK = 2
    MAXLOCALS = 4
}


 ================================================
functionDefStatement
IdentifierExpression
IE object
funcCallEx
 JVM Bytecode ===================================

// class version 49.0 (49)
// access flags 0x1
public class edu/montana/csci/csci466/bytecode/CatScriptProgram58 extends edu/montana/csci/csci468/parser/statements/CatScriptProgram {


  // access flags 0x1
  public <init>()V
    ALOAD 0
    INVOKESPECIAL edu/montana/csci/csci468/parser/statements/CatScriptProgram.<init> ()V
    RETURN
    MAXSTACK = 1
    MAXLOCALS = 1

  // access flags 0x1
  public execute()V
    ALOAD 0
    LDC 1
    INVOKESTATIC java/lang/Integer.valueOf (I)Ljava/lang/Integer;
    LDC 2
    INVOKESTATIC java/lang/Integer.valueOf (I)Ljava/lang/Integer;
    LDC 3
    INVOKESTATIC java/lang/Integer.valueOf (I)Ljava/lang/Integer;
    INVOKEVIRTUAL edu/montana/csci/csci466/bytecode/CatScriptProgram58.foo (Ljava/lang/Object;Ljava/lang/Object;Ljava/lang/Object;)V
    RETURN
    MAXSTACK = 4
    MAXLOCALS = 1

  // access flags 0x1
  public foo(Ljava/lang/Object;Ljava/lang/Object;Ljava/lang/Object;)V
    ALOAD 0
    ALOAD 3
    INVOKEVIRTUAL edu/montana/csci/csci466/bytecode/CatScriptProgram58.print (Ljava/lang/Object;)V
    RETURN
    MAXSTACK = 2
    MAXLOCALS = 4
}


 ================================================
functionDefStatement
returnStatement
funcCallEx
functionDefStatement
returnStatement
returnStatement
funcCallEx
 JVM Bytecode ===================================

// class version 49.0 (49)
// access flags 0x1
public class edu/montana/csci/csci466/bytecode/CatScriptProgram60 extends edu/montana/csci/csci468/parser/statements/CatScriptProgram {


  // access flags 0x1
  public <init>()V
    ALOAD 0
    INVOKESPECIAL edu/montana/csci/csci468/parser/statements/CatScriptProgram.<init> ()V
    RETURN
    MAXSTACK = 1
    MAXLOCALS = 1

  // access flags 0x1
  public execute()V
    ALOAD 0
    ALOAD 0
    INVOKEVIRTUAL edu/montana/csci/csci466/bytecode/CatScriptProgram60.foo ()Ljava/util/List;
    INVOKEVIRTUAL edu/montana/csci/csci466/bytecode/CatScriptProgram60.print (Ljava/lang/Object;)V
    RETURN
    MAXSTACK = 2
    MAXLOCALS = 1

  // access flags 0x1
  public foo()Ljava/util/List;
    LDC 1
    IFEQ L0
    NEW java/util/ArrayList
    DUP
    INVOKESPECIAL java/util/ArrayList.<init> ()V
    DUP
    LDC 1
    INVOKESTATIC java/lang/Integer.valueOf (I)Ljava/lang/Integer;
    INVOKEVIRTUAL java/util/ArrayList.add (Ljava/lang/Object;)Z
    POP
    DUP
    LDC 2
    INVOKESTATIC java/lang/Integer.valueOf (I)Ljava/lang/Integer;
    INVOKEVIRTUAL java/util/ArrayList.add (Ljava/lang/Object;)Z
    POP
    DUP
    LDC 3
    INVOKESTATIC java/lang/Integer.valueOf (I)Ljava/lang/Integer;
    INVOKEVIRTUAL java/util/ArrayList.add (Ljava/lang/Object;)Z
    POP
    ARETURN
   L1
   FRAME FULL [] [java/lang/Throwable]
    NOP
    NOP
    ATHROW
   L0
   FRAME FULL [edu/montana/csci/csci466/bytecode/CatScriptProgram60] []
    ACONST_NULL
    ARETURN
    MAXSTACK = 3
    MAXLOCALS = 1
}


 ================================================
functionDefStatement
returnStatement
funcCallEx
functionDefStatement
returnStatement
funcCallEx
 JVM Bytecode ===================================

// class version 49.0 (49)
// access flags 0x1
public class edu/montana/csci/csci466/bytecode/CatScriptProgram62 extends edu/montana/csci/csci468/parser/statements/CatScriptProgram {


  // access flags 0x1
  public <init>()V
    ALOAD 0
    INVOKESPECIAL edu/montana/csci/csci468/parser/statements/CatScriptProgram.<init> ()V
    RETURN
    MAXSTACK = 1
    MAXLOCALS = 1

  // access flags 0x1
  public execute()V
    ALOAD 0
    ALOAD 0
    INVOKEVIRTUAL edu/montana/csci/csci466/bytecode/CatScriptProgram62.foo ()Ljava/util/List;
    INVOKEVIRTUAL edu/montana/csci/csci466/bytecode/CatScriptProgram62.print (Ljava/lang/Object;)V
    RETURN
    MAXSTACK = 2
    MAXLOCALS = 1

  // access flags 0x1
  public foo()Ljava/util/List;
    NEW java/util/ArrayList
    DUP
    INVOKESPECIAL java/util/ArrayList.<init> ()V
    DUP
    LDC 1
    INVOKESTATIC java/lang/Integer.valueOf (I)Ljava/lang/Integer;
    INVOKEVIRTUAL java/util/ArrayList.add (Ljava/lang/Object;)Z
    POP
    DUP
    LDC 2
    INVOKESTATIC java/lang/Integer.valueOf (I)Ljava/lang/Integer;
    INVOKEVIRTUAL java/util/ArrayList.add (Ljava/lang/Object;)Z
    POP
    DUP
    LDC 3
    INVOKESTATIC java/lang/Integer.valueOf (I)Ljava/lang/Integer;
    INVOKEVIRTUAL java/util/ArrayList.add (Ljava/lang/Object;)Z
    POP
    ARETURN
    MAXSTACK = 3
    MAXLOCALS = 1
}


 ================================================
functionDefStatement
returnStatement
funcCallEx
functionDefStatement
IdentifierExpression
IE object
funcCallEx
 JVM Bytecode ===================================

// class version 49.0 (49)
// access flags 0x1
public class edu/montana/csci/csci466/bytecode/CatScriptProgram64 extends edu/montana/csci/csci468/parser/statements/CatScriptProgram {


  // access flags 0x1
  public <init>()V
    ALOAD 0
    INVOKESPECIAL edu/montana/csci/csci468/parser/statements/CatScriptProgram.<init> ()V
    RETURN
    MAXSTACK = 1
    MAXLOCALS = 1

  // access flags 0x1
  public execute()V
    ALOAD 0
    LDC 1
    INVOKESTATIC java/lang/Integer.valueOf (I)Ljava/lang/Integer;
    INVOKEVIRTUAL edu/montana/csci/csci466/bytecode/CatScriptProgram64.foo (Ljava/lang/Object;)V
    RETURN
    MAXSTACK = 2
    MAXLOCALS = 1

  // access flags 0x1
  public foo(Ljava/lang/Object;)V
    ALOAD 0
    ALOAD 1
    INVOKEVIRTUAL edu/montana/csci/csci466/bytecode/CatScriptProgram64.print (Ljava/lang/Object;)V
    RETURN
    MAXSTACK = 2
    MAXLOCALS = 2
}


 ================================================
global
functionDefStatement
funcCallEx
IdentifierExpression
 JVM Bytecode ===================================

// class version 49.0 (49)
// access flags 0x1
public class edu/montana/csci/csci466/bytecode/CatScriptProgram65 extends edu/montana/csci/csci468/parser/statements/CatScriptProgram {


  // access flags 0x2
  private I x

  // access flags 0x1
  public <init>()V
    ALOAD 0
    INVOKESPECIAL edu/montana/csci/csci468/parser/statements/CatScriptProgram.<init> ()V
    RETURN
    MAXSTACK = 1
    MAXLOCALS = 1

  // access flags 0x1
  public execute()V
    ALOAD 0
    LDC 10
    PUTFIELD edu/montana/csci/csci466/bytecode/CatScriptProgram65.x : I
    ALOAD 0
    INVOKEVIRTUAL edu/montana/csci/csci466/bytecode/CatScriptProgram65.foo ()V
    ALOAD 0
    ALOAD 0
    GETFIELD edu/montana/csci/csci466/bytecode/CatScriptProgram65.x : I
    INVOKESTATIC java/lang/Integer.valueOf (I)Ljava/lang/Integer;
    INVOKEVIRTUAL edu/montana/csci/csci466/bytecode/CatScriptProgram65.print (Ljava/lang/Object;)V
    RETURN
    MAXSTACK = 2
    MAXLOCALS = 1

  // access flags 0x1
  public foo()V
    RETURN
    MAXSTACK = 0
    MAXLOCALS = 1
}


 ================================================
functionDefStatement
IdentifierExpression
IE void
funcCallEx
 JVM Bytecode ===================================

// class version 49.0 (49)
// access flags 0x1
public class edu/montana/csci/csci466/bytecode/CatScriptProgram66 extends edu/montana/csci/csci468/parser/statements/CatScriptProgram {


  // access flags 0x1
  public <init>()V
    ALOAD 0
    INVOKESPECIAL edu/montana/csci/csci468/parser/statements/CatScriptProgram.<init> ()V
    RETURN
    MAXSTACK = 1
    MAXLOCALS = 1

  // access flags 0x1
  public execute()V
    ALOAD 0
    NEW java/util/ArrayList
    DUP
    INVOKESPECIAL java/util/ArrayList.<init> ()V
    DUP
    LDC 1
    INVOKESTATIC java/lang/Integer.valueOf (I)Ljava/lang/Integer;
    INVOKEVIRTUAL java/util/ArrayList.add (Ljava/lang/Object;)Z
    POP
    DUP
    LDC 2
    INVOKESTATIC java/lang/Integer.valueOf (I)Ljava/lang/Integer;
    INVOKEVIRTUAL java/util/ArrayList.add (Ljava/lang/Object;)Z
    POP
    DUP
    LDC 3
    INVOKESTATIC java/lang/Integer.valueOf (I)Ljava/lang/Integer;
    INVOKEVIRTUAL java/util/ArrayList.add (Ljava/lang/Object;)Z
    POP
    INVOKEVIRTUAL edu/montana/csci/csci466/bytecode/CatScriptProgram66.foo (Ljava/lang/Object;)V
    RETURN
    MAXSTACK = 4
    MAXLOCALS = 1

  // access flags 0x1
  public foo(Ljava/lang/Object;)V
    ALOAD 0
    ALOAD 1
    INVOKEVIRTUAL edu/montana/csci/csci466/bytecode/CatScriptProgram66.print (Ljava/lang/Object;)V
    RETURN
    MAXSTACK = 2
    MAXLOCALS = 2
}


 ================================================
functionDefStatement
IdentifierExpression
IE int
funcCallEx
functionDefStatement
IdentifierExpression
IE bool
funcCallEx
functionDefStatement
returnStatement
funcCallEx
[ERROR] Tests run: 15, Failures: 0, Errors: 6, Skipped: 0, Time elapsed: 0.026 s <<< FAILURE! - in edu.montana.csci.csci468.bytecode.CatscriptFunctionArgsAndReturnCompileTest
[ERROR] returnBoolWorksProperly  Time elapsed: 0.001 s  <<< ERROR!
java.lang.IllegalArgumentException: 
Error at instruction 0: Cannot pop operand off an empty stack. foo()I
00000 R  :  :     INVOKESTATIC java/lang/Boolean.valueOf (Z)Ljava/lang/Boolean;
00001 ?   :     LDC 1
00002 ?   :     INVOKESTATIC java/lang/Boolean.valueOf (Z)Ljava/lang/Boolean;
00003 ?   :     IRETURN


	at edu.montana.csci.csci468.bytecode.CatscriptFunctionArgsAndReturnCompileTest.returnBoolWorksProperly(CatscriptFunctionArgsAndReturnCompileTest.java:88)
Caused by: org.objectweb.asm.tree.analysis.AnalyzerException: Error at instruction 0: Cannot pop operand off an empty stack.
	at edu.montana.csci.csci468.bytecode.CatscriptFunctionArgsAndReturnCompileTest.returnBoolWorksProperly(CatscriptFunctionArgsAndReturnCompileTest.java:88)
Caused by: java.lang.IndexOutOfBoundsException: Cannot pop operand off an empty stack.
	at edu.montana.csci.csci468.bytecode.CatscriptFunctionArgsAndReturnCompileTest.returnBoolWorksProperly(CatscriptFunctionArgsAndReturnCompileTest.java:88)

[ERROR] returnObjectWorksProperly  Time elapsed: 0.003 s  <<< ERROR!
java.lang.IllegalArgumentException: 
Error at instruction 2: Expected I, but found R foo()Ljava/lang/Object;
00000 R  :  :     LDC 1
00001 R  : I  :     INVOKESTATIC java/lang/Integer.valueOf (I)Ljava/lang/Integer;
00002 R  : R  :     IRETURN


	at edu.montana.csci.csci468.bytecode.CatscriptFunctionArgsAndReturnCompileTest.returnObjectWorksProperly(CatscriptFunctionArgsAndReturnCompileTest.java:72)
Caused by: org.objectweb.asm.tree.analysis.AnalyzerException: Error at instruction 2: Expected I, but found R
	at edu.montana.csci.csci468.bytecode.CatscriptFunctionArgsAndReturnCompileTest.returnObjectWorksProperly(CatscriptFunctionArgsAndReturnCompileTest.java:72)
Caused by: org.objectweb.asm.tree.analysis.AnalyzerException: Expected I, but found R
	at edu.montana.csci.csci468.bytecode.CatscriptFunctionArgsAndReturnCompileTest.returnObjectWorksProperly(CatscriptFunctionArgsAndReturnCompileTest.java:72)

[ERROR] returnListWorksProperly  Time elapsed: 0.001 s  <<< ERROR!
java.lang.IllegalArgumentException: 
Error at instruction 3: Cannot pop operand off an empty stack. execute()V
00000 R  :  :     ALOAD 0
00001 R  : R  :     ALOAD 0
00002 R  : R R  :     INVOKEVIRTUAL edu/montana/csci/csci466/bytecode/CatScriptProgram63.foo ()V
00003 R  : R  :     INVOKEVIRTUAL edu/montana/csci/csci466/bytecode/CatScriptProgram63.print (Ljava/lang/Object;)V
00004 ?    :     RETURN


	at edu.montana.csci.csci468.bytecode.CatscriptFunctionArgsAndReturnCompileTest.returnListWorksProperly(CatscriptFunctionArgsAndReturnCompileTest.java:94)
Caused by: org.objectweb.asm.tree.analysis.AnalyzerException: Error at instruction 3: Cannot pop operand off an empty stack.
	at edu.montana.csci.csci468.bytecode.CatscriptFunctionArgsAndReturnCompileTest.returnListWorksProperly(CatscriptFunctionArgsAndReturnCompileTest.java:94)
Caused by: java.lang.IndexOutOfBoundsException: Cannot pop operand off an empty stack.
	at edu.montana.csci.csci468.bytecode.CatscriptFunctionArgsAndReturnCompileTest.returnListWorksProperly(CatscriptFunctionArgsAndReturnCompileTest.java:94)

[ERROR] intTypeArgWorksProperly  Time elapsed: 0.001 s  <<< ERROR!
java.lang.IllegalArgumentException: 
Error at instruction 3: Argument 1: expected I, but found R execute()V
00000 R  :  :     ALOAD 0
00001 R  : R  :     LDC 1
00002 R  : R I  :     INVOKESTATIC java/lang/Integer.valueOf (I)Ljava/lang/Integer;
00003 R  : R R  :     INVOKEVIRTUAL edu/montana/csci/csci466/bytecode/CatScriptProgram67.foo (I)V
00004 ?    :     RETURN


	at edu.montana.csci.csci468.bytecode.CatscriptFunctionArgsAndReturnCompileTest.intTypeArgWorksProperly(CatscriptFunctionArgsAndReturnCompileTest.java:32)
Caused by: org.objectweb.asm.tree.analysis.AnalyzerException: Error at instruction 3: Argument 1: expected I, but found R
	at edu.montana.csci.csci468.bytecode.CatscriptFunctionArgsAndReturnCompileTest.intTypeArgWorksProperly(CatscriptFunctionArgsAndReturnCompileTest.java:32)
Caused by: org.objectweb.asm.tree.analysis.AnalyzerException: Argument 1: expected I, but found R
	at edu.montana.csci.csci468.bytecode.CatscriptFunctionArgsAndReturnCompileTest.intTypeArgWorksProperly(CatscriptFunctionArgsAndReturnCompileTest.java:32)

[ERROR] booleanTypeArgWorksProperly  Time elapsed: 0.001 s  <<< ERROR!
java.lang.IllegalArgumentException: 
Error at instruction 3: Argument 1: expected I, but found R execute()V
00000 R  :  :     ALOAD 0
00001 R  : R  :     LDC 1
00002 R  : R I  :     INVOKESTATIC java/lang/Boolean.valueOf (Z)Ljava/lang/Boolean;
00003 R  : R R  :     INVOKEVIRTUAL edu/montana/csci/csci466/bytecode/CatScriptProgram68.foo (I)V
00004 ?    :     RETURN


	at edu.montana.csci.csci468.bytecode.CatscriptFunctionArgsAndReturnCompileTest.booleanTypeArgWorksProperly(CatscriptFunctionArgsAndReturnCompileTest.java:38)
Caused by: org.objectweb.asm.tree.analysis.AnalyzerException: Error at instruction 3: Argument 1: expected I, but found R
	at edu.montana.csci.csci468.bytecode.CatscriptFunctionArgsAndReturnCompileTest.booleanTypeArgWorksProperly(CatscriptFunctionArgsAndReturnCompileTest.java:38)
Caused by: org.objectweb.asm.tree.analysis.AnalyzerException: Argument 1: expected I, but found R
	at edu.montana.csci.csci468.bytecode.CatscriptFunctionArgsAndReturnCompileTest.booleanTypeArgWorksProperly(CatscriptFunctionArgsAndReturnCompileTest.java:38)

[ERROR] returnIntWorksProperly  Time elapsed: 0.001 s  <<< ERROR!
java.lang.IllegalArgumentException: 
Error at instruction 0: Cannot pop operand off an empty stack. foo()I
00000 R  :  :     INVOKESTATIC java/lang/Integer.valueOf (I)Ljava/lang/Integer;
00001 ?   :     LDC 1
00002 ?   :     INVOKESTATIC java/lang/Integer.valueOf (I)Ljava/lang/Integer;
00003 ?   :     IRETURN


	at edu.montana.csci.csci468.bytecode.CatscriptFunctionArgsAndReturnCompileTest.returnIntWorksProperly(CatscriptFunctionArgsAndReturnCompileTest.java:82)
Caused by: org.objectweb.asm.tree.analysis.AnalyzerException: Error at instruction 0: Cannot pop operand off an empty stack.
	at edu.montana.csci.csci468.bytecode.CatscriptFunctionArgsAndReturnCompileTest.returnIntWorksProperly(CatscriptFunctionArgsAndReturnCompileTest.java:82)
Caused by: java.lang.IndexOutOfBoundsException: Cannot pop operand off an empty stack.
	at edu.montana.csci.csci468.bytecode.CatscriptFunctionArgsAndReturnCompileTest.returnIntWorksProperly(CatscriptFunctionArgsAndReturnCompileTest.java:82)

[INFO] 
[INFO] Results:
[INFO] 
[ERROR] Errors: 
[ERROR]   CatscriptFunctionArgsAndReturnCompileTest.booleanTypeArgWorksProperly:38->CatscriptTestBase.compile:121  IllegalArgument
[ERROR]   CatscriptFunctionArgsAndReturnCompileTest.intTypeArgWorksProperly:32->CatscriptTestBase.compile:121  IllegalArgument
[ERROR]   CatscriptFunctionArgsAndReturnCompileTest.returnBoolWorksProperly:88->CatscriptTestBase.compile:121  IllegalArgument
[ERROR]   CatscriptFunctionArgsAndReturnCompileTest.returnIntWorksProperly:82->CatscriptTestBase.compile:121  IllegalArgument
[ERROR]   CatscriptFunctionArgsAndReturnCompileTest.returnListWorksProperly:94->CatscriptTestBase.compile:121  IllegalArgument
[ERROR]   CatscriptFunctionArgsAndReturnCompileTest.returnObjectWorksProperly:72->CatscriptTestBase.compile:121  IllegalArgument
[ERROR]   CatscriptStatementExecutionTest.recursiveFunctionWorksProperly:72->CatscriptTestBase.compile:121  IllegalArgument
[ERROR]   CatscriptStatementExecutionTest.returnStatementWorks:85->CatscriptTestBase.compile:121  IllegalArgument
[ERROR]   CatscriptStatementExecutionTest.varInsideFunctionWorksProperly:48->CatscriptTestBase.compile:121  IllegalArgument
[INFO] 
[ERROR] Tests run: 32, Failures: 0, Errors: 9, Skipped: 0
[INFO] 
[INFO] ------------------------------------------------------------------------
[INFO] BUILD FAILURE
[INFO] ------------------------------------------------------------------------
[INFO] Total time:  2.314 s
[INFO] Finished at: 2024-04-30T07:37:10-06:00
[INFO] ------------------------------------------------------------------------
[ERROR] Failed to execute goal org.apache.maven.plugins:maven-surefire-plugin:2.22.1:test (default-test) on project csci-468-spring2024-private: There are test failures.
[ERROR] 
[ERROR] Please refer to /Users/carson/Projects/msu/csci-468-spring2024/grading/scripts/repos/cooper_senior/target/surefire-reports for the individual test results.
[ERROR] Please refer to dump files (if any exist) [date].dump, [date]-jvmRun[N].dump and [date].dumpstream.
[ERROR] -> [Help 1]
[ERROR] 
[ERROR] To see the full stack trace of the errors, re-run Maven with the -e switch.
[ERROR] Re-run Maven using the -X switch to enable full debug logging.
[ERROR] 
[ERROR] For more information about the errors and possible solutions, please read the following articles:
[ERROR] [Help 1] http://cwiki.apache.org/confluence/display/MAVEN/MojoFailureException
